neomodel/__init__.py
neomodel/cardinality.py
neomodel/config.py
neomodel/core.py
neomodel/exception.py
neomodel/exceptions.py
neomodel/hooks.py
neomodel/match.py
neomodel/match_q.py
neomodel/properties.py
neomodel/relationship.py
neomodel/relationship_manager.py
neomodel/util.py
neomodel/contrib/__init__.py
neomodel/contrib/semi_structured.py
neomodel/contrib/spatial_properties.py
neomodel_researchly-4.0.1.data/scripts/neomodel_install_labels
neomodel_researchly-4.0.1.data/scripts/neomodel_remove_labels
neomodel_researchly-4.0.1.dist-info/AUTHORS.txt
neomodel_researchly-4.0.1.dist-info/LICENSE
neomodel_researchly-4.0.1.dist-info/METADATA
neomodel_researchly-4.0.1.dist-info/WHEEL
neomodel_researchly-4.0.1.dist-info/top_level.txt
neomodel_researchly-4.0.1.dist-info/zip-safe
neomodel_researchly-4.0.1.dist-info/RECORD
