Metadata-Version: 2.1
Name: neomodel-researchly
Version: 4.0.1
Summary: An object mapper for the neo4j graph database.
Home-page: http://github.com/neo4j-contrib/neomodel
Author: Robin Edwards
Author-email: robin.ge@gmail.com
License: MIT
Keywords: graph neo4j ORM OGM
Platform: UNKNOWN
Classifier: Development Status :: 5 - Production/Stable
Classifier: Intended Audience :: Developers
Classifier: Operating System :: OS Independent
Classifier: License :: OSI Approved :: MIT License
Classifier: Programming Language :: Python
Classifier: Topic :: Software Development :: Libraries :: Python Modules
Classifier: Programming Language :: Python :: 3.5
Classifier: Programming Language :: Python :: 3.6
Classifier: Programming Language :: Python :: 3.7
Classifier: Programming Language :: Python :: 3.8
Classifier: Topic :: Database
Requires-Dist: neo4j-driver (==4.1.1)
Requires-Dist: pytz (>=2016.10)
Requires-Dist: neobolt (==1.7.17)
Requires-Dist: pytest (>=6.0.1)
Requires-Dist: Shapely (==1.7.1)
